aiida_submission_controller/__init__.py
aiida_submission_controller/base.py
aiida_submission_controller/from_group.py
aiida_submission_controller-0.3.0.dist-info/LICENSE
aiida_submission_controller-0.3.0.dist-info/WHEEL
aiida_submission_controller-0.3.0.dist-info/METADATA
aiida_submission_controller-0.3.0.dist-info/RECORD
