Metadata-Version: 2.3
Name: aiida-submission-controller
Version: 0.3.0
Summary: Utilities for controlling submission flow in AiiDA
Author: Giovanni Pizzi, Austin Zadoks, Marnik Bercx
Requires-Python: >=3.9
Classifier: Development Status :: 4 - Beta
Classifier: Framework :: AiiDA
Classifier: License :: OSI Approved :: MIT License
Classifier: Operating System :: POSIX :: Linux
Classifier: Operating System :: MacOS :: MacOS X
Classifier: Programming Language :: Python
Classifier: Programming Language :: Python :: 3.9
Classifier: Programming Language :: Python :: 3.10
Classifier: Programming Language :: Python :: 3.11
Classifier: Programming Language :: Python :: 3.12
Classifier: Programming Language :: Python :: 3.13
Requires-Dist: aiida-core>=2.5
Requires-Dist: pydantic~=2.8
Requires-Dist: rich
Requires-Dist: pre-commit~=3.8 ; extra == "dev"
Requires-Dist: pylint-pydantic~=0.3.2 ; extra == "dev"
Requires-Dist: aiida-quantumespresso ; extra == "qe"
Project-URL: Source, https://github.com/aiidateam/aiida-submission-controller
Provides-Extra: dev
Provides-Extra: qe
